ezyquant/__init__.py
ezyquant/_version.py
ezyquant/connect.py
ezyquant/creator.py
ezyquant/errors.py
ezyquant/fields.py
ezyquant/reader.py
ezyquant/report.py
ezyquant/utils.py
ezyquant/validators.py
ezyquant/backtesting/__init__.py
ezyquant/backtesting/_backtesting.py
ezyquant/backtesting/account.py
ezyquant/backtesting/backtesting.py
ezyquant/backtesting/context.py
ezyquant/backtesting/position.py
ezyquant/backtesting/trade.py
ezyquant/indicators/__init__.py
ezyquant/indicators/pivot_point.py
ezyquant/indicators/rsi_divergence.py
ezyquant/indicators/ta.py
ezyquant/indicators/zigzag.py
ezyquant-0.9.6.dist-info/METADATA
ezyquant-0.9.6.dist-info/WHEEL
ezyquant-0.9.6.dist-info/licenses/LICENSE
ezyquant-0.9.6.dist-info/RECORD
