Metadata-Version: 2.1
Name: ezyquant
Version: 0.9.6
Summary: Powerful Python backtesting for Thai stocks
Project-URL: Documentation, https://pydoc.ezyquant.com/
Project-URL: Issues, https://github.com/ezyquant/ezyquant/issues
Project-URL: Source, https://github.com/ezyquant/ezyquant
Author-email: "Fintech (Thailand) Company Limited" <admin@fintech.co.th>
License-Expression: MIT
License-File: LICENSE
Classifier: Intended Audience :: Financial and Insurance Industry
Classifier: Intended Audience :: Science/Research
Classifier: License :: OSI Approved :: MIT License
Classifier: Programming Language :: Python
Classifier: Programming Language :: Python :: 3.8
Classifier: Programming Language :: Python :: 3.9
Classifier: Programming Language :: Python :: 3.10
Classifier: Programming Language :: Python :: 3.11
Classifier: Topic :: Office/Business :: Financial
Classifier: Topic :: Office/Business :: Financial :: Investment
Classifier: Topic :: Scientific/Engineering
Classifier: Topic :: Scientific/Engineering :: Information Analysis
Requires-Python: >=3.8
Requires-Dist: ipython
Requires-Dist: pandas>=1.5
Requires-Dist: psycopg2-binary>=2.9
Requires-Dist: python-dotenv>=1.0
Requires-Dist: quantstats>=0.0.62
Requires-Dist: sqlalchemy>=2.0
Requires-Dist: ta>=0.10
Requires-Dist: typing-extensions>=4.4
Requires-Dist: xlsxwriter>=3.0
Provides-Extra: dev
Requires-Dist: black[jupyter]~=23.0; extra == 'dev'
Requires-Dist: coverage[toml]~=7.2; extra == 'dev'
Requires-Dist: docformatter[tomli]~=1.0; extra == 'dev'
Requires-Dist: ezyquant-execution; extra == 'dev'
Requires-Dist: hatch; extra == 'dev'
Requires-Dist: pytest-env~=0.8; extra == 'dev'
Requires-Dist: pytest-kwparametrize~=0.0; extra == 'dev'
Requires-Dist: pytest-xdist[psutil]~=3.0; extra == 'dev'
Requires-Dist: pytest~=7.0; extra == 'dev'
Requires-Dist: ruff~=0.0; extra == 'dev'
Requires-Dist: sphinx-book-theme~=1.0; extra == 'dev'
Requires-Dist: sphinx~=6.2; extra == 'dev'
